openlxp_authentication/__init__.py
openlxp_authentication/admin.py
openlxp_authentication/apps.py
openlxp_authentication/models.py
openlxp_authentication/serializers.py
openlxp_authentication/urls.py
openlxp_authentication/views.py
openlxp_authentication/migrations/0001_initial.py
openlxp_authentication/migrations/__init__.py
openlxp_authentication-1.1.4.dist-info/LICENSE
openlxp_authentication-1.1.4.dist-info/METADATA
openlxp_authentication-1.1.4.dist-info/WHEEL
openlxp_authentication-1.1.4.dist-info/top_level.txt
openlxp_authentication-1.1.4.dist-info/RECORD
