Metadata-Version: 2.1
Name: openlxp-authentication
Version: 1.1.4
Summary: Installable OpenLXP Authentication that adds support for SAML
Home-page: https://github.com/OpenLXP/openlxp-authentication/
Author: OpenLXP
Author-email: openlxphost@gmail.com
License: MIT
Classifier: Development Status :: 4 - Beta
Classifier: Environment :: Web Environment
Classifier: Framework :: Django :: 3.2
Classifier: Intended Audience :: Developers
Classifier: License :: OSI Approved :: MIT License
Classifier: Operating System :: OS Independent
Classifier: Programming Language :: Python :: 3 :: Only
Classifier: Programming Language :: Python :: 3.7
Classifier: Programming Language :: Python :: Implementation :: CPython
Classifier: Topic :: Software Development :: Libraries :: Application Frameworks
Classifier: Topic :: Software Development :: Libraries :: Python Modules
Requires-Python: >=3.7
License-File: LICENSE
Requires-Dist: social-auth-app-django >=5.4.1
Requires-Dist: social-auth-core[all] >=4.1.0
Requires-Dist: djangorestframework >=3.13.0
